Data/__init__.py
Data/additional-genes.fasta
Data/archived-2024-10-21-additional-genes.fasta
Data/archived-2024-10-22-additional-genes.fasta
Data/archived-2024-10-23-additional-genes.fasta
Data/archived-2024-11-11-additional-genes.fasta
Data/archived-2025-02-24-additional-genes.fasta
Data/linkers.tsv
Data/novel-TCR-alleles-2024-10-17_v0.6.2_GENEDB-202440-7.fasta
Data/novel-TCR-alleles-2024-10-17_v0.6.2_GENEDB-202440-7.tsv
Data/novel-TCR-alleles-2025-02-20_v0.6.2_GENEDB-20255-7.fasta
Data/novel-TCR-alleles-2025-02-20_v0.6.2_GENEDB-20255-7.tsv
Data/GUI-Examples/__init__.py
Data/GUI-Examples/cat_TRG-TRD.tsv
Data/GUI-Examples/cow_TRG-TRD.tsv
Data/GUI-Examples/dog_TRA-TRB.tsv
Data/GUI-Examples/dog_TRG-TRD.tsv
Data/GUI-Examples/dolphin_TRA-TRB.tsv
Data/GUI-Examples/dolphin_TRG-TRD.tsv
Data/GUI-Examples/dromedary_TRA-TRB.tsv
Data/GUI-Examples/dromedary_TRG-TRD.tsv
Data/GUI-Examples/human_TRA-TRB.tsv
Data/GUI-Examples/human_TRG-TRD.tsv
Data/GUI-Examples/mouse_TRA-TRB.tsv
Data/GUI-Examples/mouse_TRG-TRD.tsv
Data/GUI-Examples/pig_TRA-TRB.tsv
Data/GUI-Examples/rabbit_TRG-TRD.tsv
Data/GUI-Examples/rhesus_monkey_TRA-TRB.tsv
Data/GUI-Examples/sheep_TRG-TRD.tsv
Data/kazusa/CAT.txt
Data/kazusa/COW.txt
Data/kazusa/CYNOLOGOUS_MONKEY.txt
Data/kazusa/DOG.txt
Data/kazusa/DOLPHIN.txt
Data/kazusa/DROMEDARY.txt
Data/kazusa/FERRET.txt
Data/kazusa/HUMAN.txt
Data/kazusa/MOUSE.txt
Data/kazusa/PIG.txt
Data/kazusa/RABBIT.txt
Data/kazusa/RHESUS_MONKEY.txt
Data/kazusa/SHEEP.txt
Data/kazusa/__init__.py
Stitchr/__init__.py
Stitchr/gui_stitchr.py
Stitchr/stitchr.py
Stitchr/stitchrdl.py
Stitchr/stitchrfunctions.py
Stitchr/thimble.py
stitchr-1.3.1.dist-info/licenses/LICENSE
tests/__init__.py
tests/test_shared_functions.py
stitchr-1.3.1.dist-info/METADATA
stitchr-1.3.1.dist-info/WHEEL
stitchr-1.3.1.dist-info/entry_points.txt
stitchr-1.3.1.dist-info/top_level.txt
stitchr-1.3.1.dist-info/RECORD
