Metadata-Version: 2.4
Name: stitchr
Version: 1.3.1
Summary: Stitch together coding TCR sequences from V/J/CDR3 information
Home-page: https://github.com/JamieHeather/stitchr
Author: Jamie Heather
Author-email: jheather@mgh.harvard.edu
License: : OSI Approved :: MIT License
Requires-Python: >=3.9
License-File: LICENSE
Requires-Dist: IMGTgeneDL>=0.6.1
Requires-Dist: importlib-resources>=1.1.0
Dynamic: license-file
